polymatrix/__init__.py
polymatrix/game.py
polymatrix/logger.py
polymatrix/main.py
polymatrix/multiplayergame.py
polymatrix/network.py
polymatrix/payoff.py
polymatrix/player.py
polymatrix/polymatrixgame.py
polymatrix/test.py
polymatrix-0.0.4.dist-info/LICENSE.txt
polymatrix-0.0.4.dist-info/METADATA
polymatrix-0.0.4.dist-info/WHEEL
polymatrix-0.0.4.dist-info/top_level.txt
polymatrix-0.0.4.dist-info/RECORD
