Metadata-Version: 2.1
Name: polymatrix
Version: 0.0.4
Summary: Tools for simulating and solving polymatrix games.
Home-page: https://github.com/python-polymatrix-games/polymatrix
Author: Oskar Person
Author-email: 
License: MIT License
Platform: UNKNOWN
Classifier: Programming Language :: Python :: 3
Classifier: License :: OSI Approved :: MIT License
Classifier: Operating System :: OS Independent
Requires-Python: >=3.6
Requires-Dist: scipy (>=1.4.0)
Requires-Dist: tqdm (>=4.41.0)
Requires-Dist: networkx (>=2.5.0)
Requires-Dist: numpy (>=1.19.0)
